saharaclient/__init__.py
saharaclient/_i18n.py
saharaclient/client.py
saharaclient/version.py
saharaclient/api/__init__.py
saharaclient/api/base.py
saharaclient/api/client.py
saharaclient/api/cluster_templates.py
saharaclient/api/clusters.py
saharaclient/api/data_sources.py
saharaclient/api/helpers.py
saharaclient/api/images.py
saharaclient/api/job_binaries.py
saharaclient/api/job_binary_internals.py
saharaclient/api/job_executions.py
saharaclient/api/job_types.py
saharaclient/api/jobs.py
saharaclient/api/node_group_templates.py
saharaclient/api/parameters.py
saharaclient/api/plugins.py
saharaclient/api/v2/__init__.py
saharaclient/api/v2/job_templates.py
saharaclient/api/v2/jobs.py
saharaclient/osc/__init__.py
saharaclient/osc/plugin.py
saharaclient/osc/utils.py
saharaclient/osc/v1/__init__.py
saharaclient/osc/v1/cluster_templates.py
saharaclient/osc/v1/clusters.py
saharaclient/osc/v1/data_sources.py
saharaclient/osc/v1/images.py
saharaclient/osc/v1/job_binaries.py
saharaclient/osc/v1/job_templates.py
saharaclient/osc/v1/job_types.py
saharaclient/osc/v1/jobs.py
saharaclient/osc/v1/node_group_templates.py
saharaclient/osc/v1/plugins.py
saharaclient/osc/v2/__init__.py
saharaclient/osc/v2/cluster_templates.py
saharaclient/osc/v2/clusters.py
saharaclient/osc/v2/data_sources.py
saharaclient/osc/v2/images.py
saharaclient/osc/v2/job_binaries.py
saharaclient/osc/v2/job_templates.py
saharaclient/osc/v2/job_types.py
saharaclient/osc/v2/jobs.py
saharaclient/osc/v2/node_group_templates.py
saharaclient/osc/v2/plugins.py
saharaclient/tests/__init__.py
saharaclient/tests/hacking/__init__.py
saharaclient/tests/hacking/checks.py
saharaclient/tests/hacking/commit_message.py
saharaclient/tests/hacking/logging_checks.py
saharaclient/tests/unit/__init__.py
saharaclient/tests/unit/base.py
saharaclient/tests/unit/test_base.py
saharaclient/tests/unit/test_cluster_templates.py
saharaclient/tests/unit/test_clusters.py
saharaclient/tests/unit/test_data_sources.py
python_saharaclient-4.2.0.dist-info/AUTHORS
python_saharaclient-4.2.0.dist-info/LICENSE
python_saharaclient-4.2.0.dist-info/METADATA
python_saharaclient-4.2.0.dist-info/WHEEL
python_saharaclient-4.2.0.dist-info/entry_points.txt
python_saharaclient-4.2.0.dist-info/pbr.json
python_saharaclient-4.2.0.dist-info/top_level.txt
python_saharaclient-4.2.0.dist-info/RECORD
