Metadata-Version: 2.1
Name: python-saharaclient
Version: 4.2.0
Summary: Client library for Sahara API
Home-page: https://docs.openstack.org/python-saharaclient/latest/
Author: OpenStack
Author-email: openstack-discuss@lists.openstack.org
License: Apache License, Version 2.0
Platform: UNKNOWN
Classifier: Environment :: OpenStack
Classifier: Intended Audience :: Information Technology
Classifier: Intended Audience :: System Administrators
Classifier: License :: OSI Approved :: Apache Software License
Classifier: Operating System :: POSIX :: Linux
Classifier: Programming Language :: Python
Classifier: Programming Language :: Python :: Implementation :: CPython
Classifier: Programming Language :: Python :: 3 :: Only
Classifier: Programming Language :: Python :: 3
Classifier: Programming Language :: Python :: 3.8
Classifier: Programming Language :: Python :: 3.9
Requires-Python: >=3.8
Requires-Dist: keystoneauth1 (>=3.4.0)
Requires-Dist: osc-lib (>=2.0.0)
Requires-Dist: oslo.i18n (>=3.20.0)
Requires-Dist: oslo.log (>=5.0.0)
Requires-Dist: oslo.serialization (>=2.25.0)
Requires-Dist: oslo.utils (>=3.33.0)
Requires-Dist: pbr (>=3.1.1)
Requires-Dist: python-openstackclient (>=5.2.0)
Requires-Dist: requests (>=2.14.2)
